Metadata-Version: 2.4
Name: markthat
Version: 1.2.14
Summary: A Python library for converting images and PDFs to Markdown or generating rich image descriptions using state-of-the-art multimodal LLMs
Author: MarkThat Contributors
License-Expression: MIT
Requires-Python: >=3.10
License-File: LICENSE
Requires-Dist: openai>=1.0.0
Requires-Dist: anthropic>=0.60.0
Requires-Dist: google-generativeai>=0.8.0
Requires-Dist: mistralai>=1.7.0
Requires-Dist: pymupdf>=1.26.0
Requires-Dist: numpy>=1.25.0
Requires-Dist: matplotlib>=3.7.0
Requires-Dist: Pillow>=10.0.0
Requires-Dist: Jinja2>=3.1.0
Requires-Dist: langchain>=0.3.27
Requires-Dist: langchain-openai>=0.3.28
Requires-Dist: langchain-anthropic>=0.3.18
Requires-Dist: langchain-google-genai>=2.0.10
Requires-Dist: langchain-mistralai>=0.2.11
Provides-Extra: llm
Requires-Dist: google-generativeai; extra == "llm"
Requires-Dist: openai; extra == "llm"
Requires-Dist: anthropic; extra == "llm"
Requires-Dist: mistralai; extra == "llm"
Provides-Extra: langchain
Requires-Dist: langchain>=0.3.27; extra == "langchain"
Requires-Dist: langchain-openai>=0.3.28; extra == "langchain"
Requires-Dist: langchain-anthropic>=0.3.18; extra == "langchain"
Requires-Dist: langchain-google-genai>=2.0.10; extra == "langchain"
Requires-Dist: langchain-mistralai>=0.2.11; extra == "langchain"
Provides-Extra: dev
Requires-Dist: pytest>=8.0.0; extra == "dev"
Requires-Dist: pytest-cov>=4.1.0; extra == "dev"
Requires-Dist: pytest-asyncio>=0.21.0; extra == "dev"
Requires-Dist: ruff>=0.4.0; extra == "dev"
Requires-Dist: black>=24.0.0; extra == "dev"
Requires-Dist: isort>=5.13.0; extra == "dev"
Requires-Dist: pre-commit>=3.5.0; extra == "dev"
Requires-Dist: mypy>=1.5.0; extra == "dev"
Dynamic: license-file
